fasttenet/__init__.py
fasttenet/fasttenet.py
fasttenet/data/__init__.py
fasttenet/data/fileio.py
fasttenet/utils/__init__.py
fasttenet/utils/utils.py
fasttenet-1.0.6.dist-info/LICENSE
fasttenet-1.0.6.dist-info/METADATA
fasttenet-1.0.6.dist-info/WHEEL
fasttenet-1.0.6.dist-info/top_level.txt
fasttenet-1.0.6.dist-info/RECORD
